whakerkit/__init__.py
whakerkit/po.py
whakerkit/uploads_manager.py
whakerkit/components/__init__.py
whakerkit/components/book.py
whakerkit/components/card.py
whakerkit/components/video_popup.py
whakerkit/config/__init__.py
whakerkit/config/pathmanager.py
whakerkit/config/settings.py
whakerkit/config/typesdealer.py
whakerkit/config/typesmapping.py
whakerkit/config/tests/__init__.py
whakerkit/config/tests/test_pathmanager.py
whakerkit/config/tests/test_settings.py
whakerkit/config/tests/test_typesdealer.py
whakerkit/config/tests/test_typesmapping.py
whakerkit/connection/__init__.py
whakerkit/connection/authentication.py
whakerkit/connection/base_authentication.py
whakerkit/connection/connection.py
whakerkit/connection/jwt_authetication.py
whakerkit/connection/ldap_authentication.py
whakerkit/connection/tests/__init__.py
whakerkit/connection/tests/test_authentication.py
whakerkit/connection/tests/test_base_authentication.py
whakerkit/connection/tests/test_connection.py
whakerkit/connection/tests/test_jwt_authentication.py
whakerkit/connection/tests/test_ldap_authentication.py
whakerkit/documents/__init__.py
whakerkit/documents/docs_filters.py
whakerkit/documents/docs_manager.py
whakerkit/documents/document.py
whakerkit/documents/document_utils.py
whakerkit/documents/tests/__init__.py
whakerkit/documents/tests/test_docsfilters.py
whakerkit/documents/tests/test_document.py
whakerkit/documents/tests/test_document_utils.py
whakerkit/documents/tests/test_documents_manager.py
whakerkit/error/__init__.py
whakerkit/error/middleware.py
whakerkit/filters/__init__.py
whakerkit/filters/basecompare.py
whakerkit/filters/basefilters.py
whakerkit/filters/datecompare.py
whakerkit/filters/filteredset.py
whakerkit/filters/numcompare.py
whakerkit/filters/strcompare.py
whakerkit/filters/tests/__init__.py
whakerkit/filters/tests/test_compare.py
whakerkit/filters/tests/test_filters.py
whakerkit/filters/tests/test_filterset.py
whakerkit/nodes/__init__.py
whakerkit/nodes/accessibility.py
whakerkit-2.1.1.dist-info/licenses/AUTHORS.md
whakerkit-2.1.1.dist-info/licenses/LICENSE.md
whakerkit-2.1.1.dist-info/METADATA
whakerkit-2.1.1.dist-info/WHEEL
whakerkit-2.1.1.dist-info/top_level.txt
whakerkit-2.1.1.dist-info/RECORD
