Metadata-Version: 2.4
Name: Whakerkit
Version: 2.1.1
Summary: The implementation of a WhakerKit project website.
Author-email: Brigitte Bigi <contact@sppas.org>
Maintainer-email: Brigitte Bigi <contact@sppas.org>
Project-URL: Documentation, https://whakerkit.sourceforge.io/
Project-URL: Homepage, https://sourceforge.net/projects/whakerkit/
Project-URL: Repository, https://git.code.sf.net/p/whakerkit/code
Keywords: python,toolkit,web,html,documents,files,filters
Classifier: Programming Language :: Python
Classifier: License :: OSI Approved :: GNU Affero General Public License v3 or later (AGPLv3+)
Classifier: Operating System :: OS Independent
Classifier: Development Status :: 5 - Production/Stable
Requires-Python: >=3.9
License-File: LICENSE.md
License-File: AUTHORS.md
Requires-Dist: WhakerPy>=1.5
Provides-Extra: authentication
Requires-Dist: ldap3; extra == "authentication"
Requires-Dist: PyJWT; extra == "authentication"
Provides-Extra: docs
Requires-Dist: pygments; extra == "docs"
Requires-Dist: markdown2; extra == "docs"
Requires-Dist: ClammingPy>=2.1; extra == "docs"
Provides-Extra: tests
Requires-Dist: coverage~=7.3.0; extra == "tests"
Requires-Dist: python-dotenv~=1.0.0; extra == "tests"
Dynamic: license-file
